df_global_search/__init__.py
df_global_search-0.1.1.dist-info/METADATA
df_global_search-0.1.1.dist-info/WHEEL
df_global_search-0.1.1.dist-info/top_level.txt
df_global_search-0.1.1.dist-info/RECORD
