Metadata-Version: 2.1
Name: df-global-search
Version: 0.1.1
Summary: Searches for a string in all columns and returns a styled DataFrame if match found. 
Home-page: https://github.com/sqlinsights/df-global-search
Author: Carlos D. Serrano
Author-email: sqlinsights@gmail.com
Requires-Python: >=3.8
Requires-Dist: pandas (>=1.5)
Requires-Dist: numpy (>=1.24)
